danbooru_utility.py
danbooru/__init__.py
danbooru/danbooru_utility.py
danbooru/lbpcascade_animeface.xml
danbooru-utility/__init__.py
danbooru-utility/danbooru_utility.py
danbooru-utility/lbpcascade_animeface.xml
danbooru_utility-0.1.20.dist-info/LICENSE.txt
danbooru_utility-0.1.20.dist-info/METADATA
danbooru_utility-0.1.20.dist-info/WHEEL
danbooru_utility-0.1.20.dist-info/entry_points.txt
danbooru_utility-0.1.20.dist-info/top_level.txt
danbooru_utility-0.1.20.dist-info/RECORD
