Metadata-Version: 2.1
Name: danbooru-utility
Version: 0.1.20
Summary: Utility for working with danbooru2018 dataset
Home-page: https://github.com/reidsanders/danbooru-utility.git
Author: Reid Sanders
Author-email: reid@reidsanders.net
License: UNKNOWN
Platform: UNKNOWN
Requires-Python: >=3.6
Requires-Dist: numpy (>=1.15.4)
Requires-Dist: opencv-python (>=3.4.3.18)
Requires-Dist: python-resize-image (>=1.1.18)
Requires-Dist: Pillow (>=5.4.1)
